setup.py
sourcetracker/__init__.py
sourcetracker/_sourcetracker.py
sourcetracker.egg-info/PKG-INFO
sourcetracker.egg-info/SOURCES.txt
sourcetracker.egg-info/dependency_links.txt
sourcetracker.egg-info/entry_points.txt
sourcetracker.egg-info/requires.txt
sourcetracker.egg-info/top_level.txt
sourcetracker/_cli/__init__.py
sourcetracker/_cli/gibbs.py