Metadata-Version: 1.1
Name: sourcetracker
Version: 2.0.1
Summary: Python implementation of the SourceTracker R package.
Home-page: http://www.biota.com
Author: Will Van Treuren
Author-email: will@biota.com
License: modified BSD
Platform: UNKNOWN
Classifier: Development Status :: 1 - Planning
Classifier: Intended Audience :: Science/Research
Classifier: Natural Language :: English
Classifier: Operating System :: MacOS :: MacOS X
Classifier: Operating System :: POSIX
Classifier: Operating System :: Unix
Classifier: Programming Language :: Python
Classifier: Programming Language :: Python :: 3.5
Classifier: Topic :: Scientific/Engineering
Classifier: Topic :: Scientific/Engineering :: Bio-Informatics
